poetry_plugin_bundle/__init__.py
poetry_plugin_bundle/bundlers/__init__.py
poetry_plugin_bundle/bundlers/bundler.py
poetry_plugin_bundle/bundlers/bundler_manager.py
poetry_plugin_bundle/bundlers/venv_bundler.py
poetry_plugin_bundle/console/__init__.py
poetry_plugin_bundle/console/commands/__init__.py
poetry_plugin_bundle/console/commands/bundle/__init__.py
poetry_plugin_bundle/console/commands/bundle/bundle_command.py
poetry_plugin_bundle/console/commands/bundle/venv.py
poetry_plugin_bundle/exceptions.py
poetry_plugin_bundle/plugin.py
poetry_plugin_bundle/utils/__init__.py
poetry_plugin_bundle/utils/platforms.py
poetry_plugin_bundle-1.7.0.dist-info/METADATA
poetry_plugin_bundle-1.7.0.dist-info/WHEEL
poetry_plugin_bundle-1.7.0.dist-info/entry_points.txt
poetry_plugin_bundle-1.7.0.dist-info/RECORD
